{"inkVersion":20,"root":[["ev",0,{"x()":"bedTime","exArgs":1},"pop","/ev","\n","ev",0,{"x()":"watchTv","exArgs":1},"pop","/ev","\n","\n","ev",{"VAR?":"Day_Of_Week"},"/ev",["du","ev",0,"==","/ev",{"->":".^.b","c":true},{"b":["pop","\n",{"->":"Monday"},{"->":"0.22"},null]}],["du","ev",1,"==","/ev",{"->":".^.b","c":true},{"b":["pop","\n",{"->":"Tuesday"},{"->":"0.22"},null]}],["du","ev",2,"==","/ev",{"->":".^.b","c":true},{"b":["pop","\n",{"->":"Wednesday"},{"->":"0.22"},null]}],["du","ev",3,"==","/ev",{"->":".^.b","c":true},{"b":["pop","\n",{"->":"Thursday"},{"->":"0.22"},null]}],["du","ev",4,"==","/ev",{"->":".^.b","c":true},{"b":["pop","\n",{"->":"Friday"},{"->":"0.22"},null]}],"pop","nop","\n",["done",{"#f":5,"#n":"g-0"}],null],"done",{"Monday":["ev",{"VAR?":"isNight"},"/ev",[{"->":".^.b","c":true},{"b":["^ ",{"->":"Monday.MondayNight"},{"->":"Monday.4"},null]}],"nop","\n","ev",{"VAR?":"FoundBus"},"/ev",[{"->":".^.b","c":true},{"b":["^ ",{"->":"Monday.Found"},{"->":"Monday.11"},null]}],[{"->":".^.b"},{"b":["^ ",{"->":"Monday.NotFound"},{"->":"Monday.11"},null]}],"nop","\n",{"Found":["^I finally figured out what bus to catch ",{"#":"speaker:Austin"},"\n","ev",2,{"x()":"makeChoice","exArgs":1},"pop","/ev","\n","^Looks like it's right around the corner.","\n","done",{"#f":1}],"NotFound":["^I dont know what bus to catch ",{"#":"speaker:Austin"},"\n","^maybe I need to ask people?","\n","^I just know im gonna get super overstimulated","\n","done",{"#f":1}],"MondayNight":["^alright, it's pretty late, ",{"#":"speaker:Austin"},"\n","^i'm just gonna go home","\n","ev",1,{"x()":"busChosen","exArgs":1},"pop","/ev","\n","done",{"#f":1}],"#f":1}],"Tuesday":["ev",{"VAR?":"FoundBus"},"/ev",[{"->":".^.b","c":true},{"b":["^ ",{"->":".^.^.^.Found"},{"->":".^.^.^.5"},null]}],[{"->":".^.b"},{"b":["^ ",{"->":".^.^.^.NotFound"},{"->":".^.^.^.5"},null]}],"nop","\n",{"Found":["^838, 838, thats the bus I need to take ",{"#":"speaker:Austin"},"\n","ev",2,{"x()":"makeChoice","exArgs":1},"pop","/ev","\n","^Here is is, right on time.","\n","done",{"#f":1}],"NotFound":["^Oh great...wrong bus","\n","^lets just cross 519 off the list.","\n","^I Need to find out what bus I need to catch ",{"#":"speaker:Austin"},"\n","^but talking to people just drains me.","\n","done","done",{"#f":1}],"#f":1}],"Wednesday":["done",{"#f":1}],"Thursday":["done",{"#f":1}],"Friday":["done",{"#f":1}],"global decl":["ev",2,{"VAR=":"Day_Of_Week"},false,{"VAR=":"cafeOnMonday"},false,{"VAR=":"busOnMonday"},"str","^","/str",{"VAR=":"sceneInDay"},0,{"VAR=":"calendar_Interactions"},0,{"VAR=":"bedside_Interactions"},false,{"VAR=":"isBedTime"},0,{"VAR=":"fridge_Interactions"},false,{"VAR=":"hasEatenDinner"},false,{"VAR=":"isNight"},false,{"VAR=":"bus_Chosen"},false,{"VAR=":"isLateToClass"},false,{"VAR=":"FoundBus"},false,{"VAR=":"tuesdayUni"},0,{"VAR=":"noah_Interractions"},false,{"VAR=":"spokenToNoah"},false,{"VAR=":"noahInCafe"},false,{"VAR=":"deepConversation"},false,{"VAR=":"deepConvoPause"},"str","^","/str",{"VAR=":"drink"},"str","^","/str",{"VAR=":"size"},0,{"VAR=":"cost"},false,{"VAR=":"orderedDrink"},0,{"VAR=":"clothesChosen"},0,{"VAR=":"costOfClothes"},false,{"VAR=":"spokenToMiller"},false,{"VAR=":"houseNPC1"},0,{"VAR=":"donnyInteractions"},false,{"VAR=":"houseNPC2"},0,{"VAR=":"charlesInteractions"},false,{"VAR=":"houseNPC3"},0,{"VAR=":"sanjayInteractions"},false,{"VAR=":"townNPC1"},2,{"VAR=":"town1"},false,{"VAR=":"townNPC2"},2,{"VAR=":"town2"},false,{"VAR=":"townNPC3"},2,{"VAR=":"town3"},false,{"VAR=":"NoahWednesdayTown"},0,{"VAR=":"giftsBought"},false,{"VAR=":"boughtForNoah"},false,{"VAR=":"brainyGizato"},"/ev","end",null],"#f":1}],"listDefs":{}}